LICENSE
README.md
setup.py
NlpToolkit_SentiNet.egg-info/PKG-INFO
NlpToolkit_SentiNet.egg-info/SOURCES.txt
NlpToolkit_SentiNet.egg-info/dependency_links.txt
NlpToolkit_SentiNet.egg-info/top_level.txt
SentiNet/PolarityType.py
SentiNet/SentiLiteral.py
SentiNet/SentiLiteralNet.py
SentiNet/SentiNet.py
SentiNet/SentiSynSet.py
SentiNet/__init__.py
SentiNet/data/__init__.py
SentiNet/data/turkish_sentiliteralnet.xml
SentiNet/data/turkish_sentinet.xml
test/SentiLiteralNetTest.py
test/SentiNetTest.py
test/SentiSynSetTest.py
test/__init__.py