Metadata-Version: 2.1
Name: NlpToolkit-SentiNet
Version: 1.0.17
Summary: Turkish SentiNet
Home-page: https://github.com/StarlangSoftware/TurkishSentiNet-Py
Author: olcaytaner
Author-email: olcay.yildiz@ozyegin.edu.tr
License: UNKNOWN
Platform: UNKNOWN
License-File: LICENSE
